{
  "exam_id": "gcp-pcd",
  "overview": "The Professional Cloud Developer exam validates the ability to design, develop, and manage scalable, reliable, and secure cloud-native applications on Google Cloud. It focuses on the full application lifecycle, from choosing the right compute and storage options to implementing CI/CD pipelines and monitoring application health.\n\nThis certification is intended for developers who have experience building applications with Google Cloud services and understand the nuances of microservices, containerization, and serverless architectures. Prerequisites include a strong grasp of programming languages and general cloud computing principles.",
  "difficulty_rating": 4,
  "average_study_weeks": 8,
  "cost_usd": 200,
  "validity_years": 2,
  "recertification_info": "To recertify, candidates must retake the current version of the Professional Cloud Developer exam before their current certification expires.",
  "official_resources": [
    {
      "title": "Professional Cloud Developer Exam Guide",
      "url": "https://cloud.google.com/learn/certification/cloud-developer",
      "type": "exam_guide"
    },
    {
      "title": "Google Cloud Skills Boost - Cloud Developer Learning Path",
      "url": "https://www.cloudskillsboost.google/",
      "type": "training"
    },
    {
      "title": "Google Cloud Documentation",
      "url": "https://cloud.google.com/docs",
      "type": "docs"
    },
    {
      "title": "Official Sample Questions",
      "url": "https://cloud.google.com/learn/certification/cloud-developer",
      "type": "practice"
    }
  ],
  "preparation_tips": [
    "Master the differences between App Engine Standard and Flexible environments.",
    "Understand GKE deployment strategies, including Rolling Updates and Canary deployments.",
    "Deep dive into Cloud Run for serverless containerized applications and its scaling behavior.",
    "Study the specific use cases for Cloud Spanner vs. Cloud SQL vs. Firestore.",
    "Practice implementing Cloud Pub/Sub for asynchronous messaging and event-driven architectures.",
    "Learn how to use Cloud Logging and Cloud Monitoring for debugging and performance tuning.",
    "Review the Google Cloud SDK (gcloud) commands for deploying and managing resources.",
    "Understand the principles of 12-Factor App methodology and how they apply to GCP.",
    "Practice writing and optimizing queries for BigQuery and Firestore.",
    "Explore Identity and Access Management (IAM) roles specifically for service accounts used by applications."
  ],
  "exam_day_tips": [
    "Carefully read the scenario to determine if the priority is cost, speed of deployment, or high availability.",
    "Eliminate obviously wrong answers by identifying services that don't fit the technical requirements.",
    "Manage your time strictly; if a question is too complex, flag it and move on.",
    "Look for keywords like 'minimal operational overhead' which usually point toward serverless options.",
    "Ensure you are comfortable with the online proctoring environment and system requirements before starting.",
    "Read all multiple-choice options before selecting the answer, as some may be 'more' correct than others."
  ],
  "recommended_experience": "3+ years of industry experience including 1+ year of designing and managing solutions using Google Cloud Platform.",
  "related_certifications": [
    {
      "code": "gcp-ace",
      "name": "Associate Cloud Engineer",
      "relationship": "prerequisite"
    },
    {
      "code": "gcp-pca",
      "name": "Professional Cloud Architect",
      "relationship": "complementary"
    },
    {
      "code": "gcp-pda",
      "name": "Professional Data Engineer",
      "relationship": "next_step"
    }
  ],
  "key_services_to_know": [
    "Google Kubernetes Engine (GKE)",
    "Cloud Run",
    "App Engine",
    "Cloud Functions",
    "Cloud Spanner",
    "Cloud SQL",
    "Firestore",
    "Cloud Pub/Sub",
    "Cloud Storage",
    "Cloud Logging",
    "Cloud Monitoring",
    "Cloud Build",
    "Identity and Access Management (IAM)",
    "BigQuery",
    "Cloud Endpoints/API Gateway"
  ]
}