{
  "id": "comptia-a-core2",
  "provider": "comptia",
  "name": "CompTIA A+ Core 2",
  "code": "220-1202",
  "description": "Validates skills in operating systems, security, software troubleshooting, and operational procedures for IT support roles.",
  "total_questions": 90,
  "time_limit_minutes": 90,
  "passing_score_pct": 75,
  "domains": [
    {"id": "operating-systems", "name": "Operating Systems", "weight_pct": 25},
    {"id": "security", "name": "Security", "weight_pct": 25},
    {"id": "software-troubleshooting", "name": "Software Troubleshooting", "weight_pct": 22},
    {"id": "operational-procedures", "name": "Operational Procedures", "weight_pct": 28}
  ],
  "exam_guide_url": "https://www.comptia.org/certifications/a"
}
